betterreads/__init__.py
betterreads/author.py
betterreads/book.py
betterreads/client.py
betterreads/comment.py
betterreads/event.py
betterreads/group.py
betterreads/owned_book.py
betterreads/request.py
betterreads/review.py
betterreads/session.py
betterreads/user.py
betterreads/user_shelf.py
betterreads-0.4.2.dist-info/LICENSE
betterreads-0.4.2.dist-info/METADATA
betterreads-0.4.2.dist-info/WHEEL
betterreads-0.4.2.dist-info/top_level.txt
betterreads-0.4.2.dist-info/RECORD
