Metadata-Version: 2.1
Name: betterreads
Version: 0.4.2
Summary: Python 3 wrapper for Goodreads API
Home-page: https://github.com/thejessleigh/betterreads
Author: Jess Unrein
Author-email: j.l.unrein@gmail.com
License: MIT
Keywords: goodreads API
Platform: UNKNOWN
Classifier: Development Status :: 4 - Beta
Classifier: Intended Audience :: Developers
Classifier: License :: OSI Approved :: MIT License
Classifier: Natural Language :: English
Classifier: Programming Language :: Python :: 3.6
Classifier: Programming Language :: Python :: 3.7
Requires-Dist: backports-datetime-fromisoformat
Requires-Dist: rauth
Requires-Dist: requests
Requires-Dist: xmltodict
